[
 {
    "id": "melted_bloodrune",
    "type": "GENERIC",
    "category": "spare_parts",
    "name": "melted bloodrune stone",
    "description": "Finely crushed and extremely heated bloodrune stone. It merely generates a faint glow, but the most important, the power still possessed in its liquid phase.",
    "weight": 750,
    "volume": 1,
    "price": 0,
    "price_postapoc": 0,
    "material": [ "compactblood" ],
    "symbol": "~",
    "color": "red"
  },
 {
    "id": "bloodrune",
    "type": "GENERIC",
    "category": "spare_parts",
    "name": "bloodrune stone",
    "description": "A pleasant, red colored stone that looks like a pure, solidified vampire blood. Its core imitates a heartbeat with unreadable marks appearing again and again from its outside layer. The strange power seems to be used with certain crafts.",
    "weight": 750,
    "volume": 1,
    "price": 0,
    "price_postapoc": 500000,
    "count": 3,
    "material": [ "compactblood" ],
    "symbol": ".",
    "color": "red"
  },
  {
    "id": "bigbloodrune",
    "type": "GENERIC",
    "category": "spare_parts",
    "name": "large bloodrune stone",
    "description": "A large bloodrune stone. Too big for usual crafts and requires breaking into pieces with a proper tool to be usable.",
    "weight": 3000,
    "volume": 7,
    "price": 0,
    "price_postapoc": 2500000,
    "material": [ "compactblood" ],
    "symbol": ".",
    "color": "red"
  },
  {
    "id": "stickyblood",
    "type": "GENERIC",
    "category": "spare_parts",
    "name": "sticky blood",
    "description": "A sticky, rounded human blood, as literally. Its clarity red seems clean enough to look throught it while stretchy and the original form remains.",
    "weight": 250,
    "volume": 1,
    "price": 0,
    "price_postapoc": 200000,
    "material": [ "compactblood" ],
    "symbol": "o",
    "color": "red"
  },
  {
    "id": "bloodpowder",
    "type": "COMESTIBLE",
    "comestible_type": "FOOD",
    "name": "blood powder",
    "description": "A powdered human blood. Perfect vampire getaway snacks.",
    "weight": 10,
    "volume": 0,
    "price": 1,
    "count": 10,
    "quench" : 1,
    "healthy" : -3,
    "nutrition" : 3,
    "material": [ "hflesh" ],
    "symbol": "'",
    "color": "red"
  },
  {
    "id": "bloodextract",
    "type": "COMESTIBLE",
    "comestible_type": "FOOD",
    "name": "blood extract",
    "description": "A sticky sap after the process of extraction from the blood.",
    "weight": 40,
    "volume": 1,
    "price": 0,
    "quench" : 5,
    "healthy" : -3,
    "nutrition" : -2,
    "material": [ "hflesh" ],
    "symbol": "~",
    "color": "pink",
    "count": 3
  },
  {
    "id": "compactsheet",
    "type": "GENERIC",
    "category": "spare_parts",
    "name": "blood compact sheet",
    "description": "Well compressed leathery sheet. It is known as an aesthetical clothing material, due to reddish appearance. But from now, its proven superior to armorcraft.",
    "weight": 250,
    "volume": 1,
    "price": 0,
    "material": [ "compactblood" ],
    "symbol": "#",
    "color": "red"
  },
  {
    "id": "pelletblood",
    "type": "GENERIC",
    "category": "spare_parts",
    "name": "blood pellet",
    "description": "A tiny blood pellet.",
    "weight": 10,
    "volume": 0,
    "price": 0,
    "count": 2,
    "material": [ "compactblood" ],
    "symbol": ".",
    "color": "red"
    },
    {
        "type" : "COMESTIBLE",
        "edit_mode": "modify",
        "id" : "blood",
        "name" : "blood",
        "name_plural" : "blood",
        "weight" : 265,
        "color" : "red",
        "container" : "jug_plastic",
        "comestible_type" : "DRINK",
        "symbol" : "~",
        "quench" : 5,
        "healthy" : -8,
        "nutrition" : 5,
        "description" : "Blood, possibly that of a human.  Disgusting!",
        "price" : 0,
        "material" : "hflesh",
        "volume" : 15,
        "phase" : "liquid",
        "fun" : -50
    }
 ]